<?xml version="1.0" encoding="UTF-8"?>
<Asteroid_types>
 <asteroid>
  <id>default</id>
  <gfx>asteroid-00.webp</gfx>
  <gfx>asteroid-01.webp</gfx>
  <gfx>asteroid-02.webp</gfx>
  <gfx>asteroid-03.webp</gfx>
  <gfx>asteroid-04.webp</gfx>
  <gfx>asteroid-05.webp</gfx>
  <gfx>asteroid-06.webp</gfx>
  <gfx>asteroid-07.webp</gfx>
  <gfx>asteroid-08.webp</gfx>
  <gfx>asteroid-09.webp</gfx>
  <gfx>asteroid-10.webp</gfx>
  <gfx>asteroid-11.webp</gfx>
  <gfx>asteroid-12.webp</gfx>
  <gfx>asteroid-13.webp</gfx>
  <gfx>asteroid-15.webp</gfx>
  <gfx>asteroid-16.webp</gfx>
  <gfx>asteroid-21.webp</gfx>
  <gfx>asteroid-22.webp</gfx>
  <gfx>asteroid-23.webp</gfx>
  <gfx>asteroid-24.webp</gfx>
  <armour>50</armour>
  <commodity>
   <name>Ore</name>
   <quantity>25</quantity>
  </commodity>
 </asteroid>
 <asteroid>
  <id>small</id>
  <gfx>asteroid-01.webp</gfx>
  <gfx>asteroid-02.webp</gfx>
  <gfx>asteroid-03.webp</gfx>
  <gfx>asteroid-04.webp</gfx>
  <gfx>asteroid-05.webp</gfx>
  <gfx>asteroid-06.webp</gfx>
  <gfx>asteroid-22.webp</gfx>
  <gfx>asteroid-24.webp</gfx>
  <armour>50</armour>
  <commodity>
   <name>Ore</name>
   <quantity>3</quantity>
  </commodity>
 </asteroid>
 <asteroid>
  <id>small_gold</id>
  <gfx>asteroid-00.webp</gfx>
  <gfx>asteroid-07.webp</gfx>
  <gfx>asteroid-08.webp</gfx>
  <gfx>asteroid-09.webp</gfx>
  <gfx>asteroid-10.webp</gfx>
  <gfx>asteroid-11.webp</gfx>
  <gfx>asteroid-12.webp</gfx>
  <gfx>asteroid-16.webp</gfx>
  <gfx>asteroid-21.webp</gfx>
  <armour>250</armour>
  <commodity>
   <name>Gold</name>
   <quantity>2</quantity>
  </commodity>
 </asteroid>
 <asteroid>
  <id>massive</id>
  <gfx>asteroid-00.webp</gfx>
  <gfx>asteroid-07.webp</gfx>
  <gfx>asteroid-08.webp</gfx>
  <gfx>asteroid-09.webp</gfx>
  <gfx>asteroid-10.webp</gfx>
  <gfx>asteroid-11.webp</gfx>
  <gfx>asteroid-12.webp</gfx>
  <gfx>asteroid-13.webp</gfx>
  <gfx>asteroid-14.webp</gfx>
  <gfx>asteroid-15.webp</gfx>
  <gfx>asteroid-16.webp</gfx>
  <gfx>asteroid-21.webp</gfx>
  <gfx>asteroid-23.webp</gfx>
  <armour>200</armour>
  <commodity>
   <name>Ore</name>
   <quantity>75</quantity>
  </commodity>
  <commodity>
   <name>Gold</name>
   <quantity>5</quantity>
  </commodity>
 </asteroid>
 <asteroid>
  <id>golden</id>
  <gfx>asteroid-00.webp</gfx>
  <gfx>asteroid-07.webp</gfx>
  <gfx>asteroid-08.webp</gfx>
  <gfx>asteroid-09.webp</gfx>
  <gfx>asteroid-10.webp</gfx>
  <gfx>asteroid-11.webp</gfx>
  <gfx>asteroid-12.webp</gfx>
  <gfx>asteroid-13.webp</gfx>
  <gfx>asteroid-14.webp</gfx>
  <gfx>asteroid-16.webp</gfx>
  <gfx>asteroid-21.webp</gfx>
  <armour>700</armour>
  <commodity>
   <name>Gold</name>
   <quantity>50</quantity>
  </commodity>
  <commodity>
   <name>Diamond</name>
   <quantity>5</quantity>
  </commodity>
 </asteroid>
 <asteroid>
  <id>diamond</id>
  <gfx>asteroid-00.webp</gfx>
  <gfx>asteroid-01.webp</gfx>
  <gfx>asteroid-02.webp</gfx>
  <gfx>asteroid-03.webp</gfx>
  <gfx>asteroid-04.webp</gfx>
  <gfx>asteroid-05.webp</gfx>
  <gfx>asteroid-06.webp</gfx>
  <gfx>asteroid-07.webp</gfx>
  <gfx>asteroid-08.webp</gfx>
  <gfx>asteroid-09.webp</gfx>
  <gfx>asteroid-10.webp</gfx>
  <gfx>asteroid-11.webp</gfx>
  <gfx>asteroid-12.webp</gfx>
  <gfx>asteroid-13.webp</gfx>
  <gfx>asteroid-15.webp</gfx>
  <gfx>asteroid-16.webp</gfx>
  <gfx>asteroid-21.webp</gfx>
  <gfx>asteroid-22.webp</gfx>
  <gfx>asteroid-23.webp</gfx>
  <gfx>asteroid-24.webp</gfx>
  <armour>600</armour>
  <commodity>
   <name>Diamond</name>
   <quantity>75</quantity>
  </commodity>
  <commodity>
   <name>Water</name>
   <quantity>5</quantity>
  </commodity>
 </asteroid>
 <asteroid>
  <id>liquid</id>
  <gfx>asteroid-00.webp</gfx>
  <gfx>asteroid-01.webp</gfx>
  <gfx>asteroid-02.webp</gfx>
  <gfx>asteroid-03.webp</gfx>
  <gfx>asteroid-04.webp</gfx>
  <gfx>asteroid-05.webp</gfx>
  <gfx>asteroid-06.webp</gfx>
  <gfx>asteroid-07.webp</gfx>
  <gfx>asteroid-08.webp</gfx>
  <gfx>asteroid-09.webp</gfx>
  <gfx>asteroid-10.webp</gfx>
  <gfx>asteroid-11.webp</gfx>
  <gfx>asteroid-12.webp</gfx>
  <gfx>asteroid-13.webp</gfx>
  <gfx>asteroid-14.webp</gfx>
  <gfx>asteroid-16.webp</gfx>
  <gfx>asteroid-21.webp</gfx>
  <gfx>asteroid-22.webp</gfx>
  <gfx>asteroid-24.webp</gfx>
  <armour>40</armour>
  <commodity>
   <name>Water</name>
   <quantity>75</quantity>
  </commodity>
  <commodity>
   <name>Ore</name>
   <quantity>5</quantity>
  </commodity>
 </asteroid>
</Asteroid_types>
