<?xml version="1.0" encoding="UTF-8"?>
<asset name="Naga">
 <pos>
  <x>9407.126919</x>
  <y>-2318.658043</y>
 </pos>
 <GFX>
  <space>O03.webp</space>
  <exterior>aquatic.webp</exterior>
 </GFX>
 <presence>
  <faction>Za'lek</faction>
  <value>100.000000</value>
  <range>2</range>
 </presence>
 <general>
  <class>O</class>
  <population>7500000</population>
  <services>
   <land/>
   <refuel/>
   <bar/>
   <missions/>
   <commodity/>
   <outfits/>
   <shipyard/>
  </services>
  <commodities/>
  <description>Naga is a purely aquatic planet. The land closest to the surface is under more than a mile of water. The planet is teeming with life of mind-boggling variëty and type. The planets scientific and aesthetic value makes it one of the most favored Za'lek worlds.</description>
  <bar>This bar is built on one of the upper decks of the underwater cities, with the entire ceiling beïng a window out into Naga's oceans. The sight is nothing short of breathtaking.</bar>
 </general>
 <tech>
  <item>Common Outfits</item>
  <item>Elite Missiles</item>
  <item>Turret Missiles</item>
  <item>Small Beam</item>
  <item>Medium Beam</item>
  <item>Small Mid Outfits</item>
  <item>Small Elite Outfits</item>
  <item>Medium Mid Outfits</item>
  <item>Medium Elite Outfits</item>
  <item>Couriers</item>
  <item>Freighters</item>
  <item>Za'lek Medium Ships</item>
 </tech>
</asset>
